ez_kafka/__init__.py
ez_kafka/consumer.py
ez_kafka-0.1.2.dist-info/LICENSE
ez_kafka-0.1.2.dist-info/METADATA
ez_kafka-0.1.2.dist-info/WHEEL
ez_kafka-0.1.2.dist-info/top_level.txt
ez_kafka-0.1.2.dist-info/RECORD
