Metadata-Version: 2.1
Name: ez_kafka
Version: 0.1.2
Summary: EZ consumer for Kafka
Author-email: Moein Arabi <moein.mo81@gmail.com>
License: MIT License
Project-URL: Homepage, https://github.com/ILoveBacteria/ez-kafka
Project-URL: Issues, https://github.com/ILoveBacteria/ez-kafka/issues
Classifier: Programming Language :: Python :: 3
Classifier: License :: OSI Approved :: MIT License
Classifier: Operating System :: OS Independent
Requires-Python: >=3.10
License-File: LICENSE
Requires-Dist: confluent-kafka>=2.5.0
